README.md
setup.cfg
setup.py
neural_map/__init__.py
neural_map/_check_inputs.py
neural_map/_decay_functions.py
neural_map/_neighbourhood_functions.py
neural_map/_neural_map.py
neural_map/_plot.py
neural_map/_weight_init_functions.py
neural_map.egg-info/PKG-INFO
neural_map.egg-info/SOURCES.txt
neural_map.egg-info/dependency_links.txt
neural_map.egg-info/requires.txt
neural_map.egg-info/top_level.txt
tests/__init__.py
tests/test_neural_map.py
tests/tests_decay_functions.py
tests/tests_neighbourhood_functions.py