Metadata-Version: 2.1
Name: neural-map
Version: 0.0.7
Summary: NeuralMap is a data analysis tool based on Self-Organizing Maps
Home-page: https://github.com/FrancoBobadilla/NeuralMap
Author: Franco José Bobadilla
Author-email: 1709673@ucc.edu.ar
License: MIT
Keywords: self-organizing-maps,dimensionality-reduction,machine-learning,clustering,hdbscan,kmeans-clustering,kmedoids-clustering,data-analysis,unsupervised-learning
Platform: UNKNOWN
Classifier: Programming Language :: Python :: 3
Classifier: License :: OSI Approved :: MIT License
Classifier: Operating System :: OS Independent
Requires-Python: >=3.6
